{
  "collectionName": "components_layout_footers",
  "info": {
    "displayName": "Footer",
    "description": ""
  },
  "options": {},
  "attributes": {
    "socialLinks": {
      "type": "component",
      "repeatable": true,
      "component": "links.social-link"
    },
    "LegalLink": {
      "type": "component",
      "repeatable": true,
      "component": "links.link"
    },
    "title": {
      "type": "string"
    },
    "copyright": {
      "type": "string"
    },
    "relatedLink": {
      "type": "component",
      "repeatable": true,
      "component": "links.link"
    }
  }
}
